Metadata-Version: 1.0
Name: jrfork-kegbot-pycore
Version: 0.0.1
Summary: Standalone Python Kegbot Core.
Home-page: https://kegbot.org/docs/pycore
Author: johnnyruzdev
Author-email: johnnyruzdev01@outlook.com
License: UNKNOWN
Platform: UNKNOWN
